{
    "Step3": {
        "soma": {
            "AP_height": [
                18.395450316134163,
                3.6790900632268326
            ],
            "AHP_slow_time": [
                0.2316802711710908,
                0.04633605423421816
            ],
            "ISI_CV": [
                0.10295232963055301,
                0.020590465926110604
            ],
            "doublet_ISI": [
                18.60000000000423,
                3.720000000000846
            ],
            "adaptation_index2": [
                0.007951599665966879,
                0.0015903199331933758
            ],
            "mean_frequency": [
                17.64646566503163,
                3.5292931330063264
            ],
            "AHP_depth_abs_slow": [
                -56.66169469589384,
                11.332338939178769
            ],
            "AP_width": [
                0.8599999999993932,
                0.17199999999987867
            ],
            "time_to_first_spike": [
                10.900000000093087,
                2.1800000000186173
            ],
            "AHP_depth_abs": [
                -56.65243414382368,
                11.330486828764737
            ]
        }
    },
    "Step2": {
        "soma": {
            "AP_height": [
                25.891072503943008,
                5.178214500788602
            ],
            "AHP_slow_time": [
                0.17779340291969736,
                0.035558680583939475
            ],
            "ISI_CV": [
                0.05594085615619184,
                0.011188171231238369
            ],
            "doublet_ISI": [
                36.300000000008254,
                7.260000000001651
            ],
            "adaptation_index2": [
                0.0034254745279902903,
                0.0006850949055980582
            ],
            "mean_frequency": [
                11.00660396238491,
                2.201320792476982
            ],
            "AHP_depth_abs_slow": [
                -60.82329953338293,
                12.164659906676587
            ],
            "AP_width": [
                0.8818181818175607,
                0.17636363636351216
            ],
            "time_to_first_spike": [
                24.000000000096065,
                4.800000000019214
            ],
            "AHP_depth_abs": [
                -61.65280444076118,
                12.330560888152236
            ]
        }
    },
    "Step1": {
        "soma": {
            "AP_height": [
                27.508535313395843,
                5.501707062679169
            ],
            "AHP_slow_time": [
                0.15686622873548842,
                0.03137324574709768
            ],
            "ISI_CV": [
                0.03653614930676521,
                0.007307229861353042
            ],
            "doublet_ISI": [
                52.50000000001194,
                10.500000000002387
            ],
            "adaptation_index2": [
                -0.00021544598213724762,
                4.308919642744953e-05
            ],
            "mean_frequency": [
                8.86062754092119,
                1.772125508184238
            ],
            "AHP_depth_abs_slow": [
                -61.940685166768496,
                12.3881370333537
            ],
            "AP_width": [
                0.899999999999362,
                0.1799999999998724
            ],
            "time_to_first_spike": [
                34.900000000098544,
                6.980000000019709
            ],
            "AHP_depth_abs": [
                -61.83124769316902,
                12.366249538633804
            ]
        },
        "MEA": {
            "peak_to_valley_0": [
                0.0014900000000000002,
                0.0002980000000000001
            ],
            "peak_to_valley_1": [
                0.001445,
                0.00028900000000000003
            ],
            "peak_to_valley_2": [
                0.0013950000000000002,
                0.00027900000000000006
            ],
            "peak_to_valley_3": [
                0.00135,
                0.00027
            ],
            "peak_to_valley_4": [
                0.0016400000000000002,
                0.00032800000000000006
            ],
            "peak_to_valley_5": [
                0.0018050000000000002,
                0.00036100000000000005
            ],
            "peak_to_valley_6": [
                0.0014600000000000001,
                0.00029200000000000005
            ],
            "peak_to_valley_7": [
                -0.00033000000000000005,
                6.600000000000002e-05
            ],
            "peak_to_valley_8": [
                -0.0011350000000000002,
                0.00022700000000000004
            ],
            "peak_to_valley_9": [
                -0.0014650000000000002,
                0.0002930000000000001
            ],
            "peak_to_valley_10": [
                -0.0019500000000000001,
                0.00039000000000000005
            ],
            "peak_to_valley_11": [
                -0.0031500000000000005,
                0.0006300000000000001
            ],
            "peak_to_valley_12": [
                -0.0054,
                0.00108
            ],
            "peak_to_valley_13": [
                -0.00666,
                0.001332
            ],
            "peak_to_valley_14": [
                -0.009945,
                0.0019890000000000003
            ],
            "peak_to_valley_15": [
                -0.009945,
                0.0019890000000000003
            ],
            "peak_to_valley_16": [
                -0.00995,
                0.00199
            ],
            "peak_to_valley_17": [
                -0.00995,
                0.00199
            ],
            "peak_to_valley_18": [
                -0.010015000000000001,
                0.0020030000000000004
            ],
            "peak_to_valley_19": [
                -0.010020000000000001,
                0.002004
            ],
            "peak_trough_ratio_0": [
                -0.37002536146623094,
                0.0740050722932462
            ],
            "peak_trough_ratio_1": [
                -0.4010437733931897,
                0.08020875467863794
            ],
            "peak_trough_ratio_2": [
                -0.44500388910094263,
                0.08900077782018853
            ],
            "peak_trough_ratio_3": [
                -0.5148670045427161,
                0.10297340090854322
            ],
            "peak_trough_ratio_4": [
                -0.6032141839348211,
                0.12064283678696422
            ],
            "peak_trough_ratio_5": [
                -0.58562650516541,
                0.11712530103308201
            ],
            "peak_trough_ratio_6": [
                -0.36550995430854133,
                0.07310199086170827
            ],
            "peak_trough_ratio_7": [
                -0.36798149788677836,
                0.07359629957735568
            ],
            "peak_trough_ratio_8": [
                -1.13962498511901,
                0.22792499702380198
            ],
            "peak_trough_ratio_9": [
                -1.562683387480243,
                0.31253667749604863
            ],
            "peak_trough_ratio_10": [
                -2.0784534809045145,
                0.41569069618090293
            ],
            "peak_trough_ratio_11": [
                -2.562411448812409,
                0.5124822897624818
            ],
            "peak_trough_ratio_12": [
                -2.609408764796948,
                0.5218817529593897
            ],
            "peak_trough_ratio_13": [
                -2.7464346276871225,
                0.5492869255374245
            ],
            "peak_trough_ratio_14": [
                -3.0063848785443796,
                0.601276975708876
            ],
            "peak_trough_ratio_15": [
                -3.292546260514953,
                0.6585092521029906
            ],
            "peak_trough_ratio_16": [
                -4.589801564274073,
                0.9179603128548147
            ],
            "peak_trough_ratio_17": [
                -15.126819788733496,
                3.0253639577466993
            ],
            "peak_trough_ratio_18": [
                144.03297175340492,
                28.806594350680985
            ],
            "peak_trough_ratio_19": [
                75.43370562399892,
                15.086741124799785
            ],
            "halfwidth_0": [
                0.0006550000000000001,
                0.000131
            ],
            "halfwidth_1": [
                0.0006500000000000001,
                0.00013000000000000002
            ],
            "halfwidth_2": [
                0.0006450000000000001,
                0.00012900000000000002
            ],
            "halfwidth_3": [
                0.0006450000000000001,
                0.00012900000000000002
            ],
            "halfwidth_4": [
                0.0006450000000000001,
                0.00012900000000000002
            ],
            "halfwidth_5": [
                0.00063,
                0.000126
            ],
            "halfwidth_6": [
                0.00039000000000000005,
                7.800000000000001e-05
            ],
            "halfwidth_7": [
                -0.0008700000000000001,
                0.00017400000000000003
            ],
            "halfwidth_8": [
                -0.0014600000000000001,
                0.00029200000000000005
            ],
            "halfwidth_9": [
                -0.00199,
                0.000398
            ],
            "halfwidth_10": [
                -0.0028450000000000003,
                0.0005690000000000001
            ],
            "halfwidth_11": [
                -0.004410000000000001,
                0.0008820000000000002
            ],
            "halfwidth_12": [
                -0.0071,
                0.0014200000000000003
            ],
            "halfwidth_13": [
                -0.008740000000000001,
                0.0017480000000000004
            ],
            "halfwidth_14": [
                -0.012430000000000002,
                0.0024860000000000004
            ],
            "halfwidth_15": [
                -0.013260000000000001,
                0.0026520000000000003
            ],
            "halfwidth_16": [
                -0.014195000000000001,
                0.0028390000000000004
            ],
            "halfwidth_17": [
                -0.015915000000000002,
                0.0031830000000000005
            ],
            "halfwidth_18": [
                -0.017490000000000002,
                0.0034980000000000007
            ],
            "halfwidth_19": [
                -0.01803,
                0.0036060000000000003
            ],
            "neg_peak_relative_0": [
                0.004176069044969843,
                0.0008352138089939686
            ],
            "neg_peak_relative_1": [
                0.0056403747576142,
                0.00112807495152284
            ],
            "neg_peak_relative_2": [
                0.008043991494177997,
                0.0016087982988355995
            ],
            "neg_peak_relative_3": [
                0.01242847820812993,
                0.0024856956416259863
            ],
            "neg_peak_relative_4": [
                0.023210922584692446,
                0.004642184516938489
            ],
            "neg_peak_relative_5": [
                0.07772804028961275,
                0.015545608057922551
            ],
            "neg_peak_relative_6": [
                1.0,
                0.2
            ],
            "neg_peak_relative_7": [
                0.3939461664616405,
                0.0787892332923281
            ],
            "neg_peak_relative_8": [
                0.20725719026363987,
                0.041451438052727975
            ],
            "neg_peak_relative_9": [
                0.05118615078455844,
                0.010237230156911688
            ],
            "neg_peak_relative_10": [
                0.017266022692226178,
                0.003453204538445236
            ],
            "neg_peak_relative_11": [
                0.006897996613040098,
                0.0013795993226080197
            ],
            "neg_peak_relative_12": [
                0.004041798930210185,
                0.000808359786042037
            ],
            "neg_peak_relative_13": [
                0.002555434738475552,
                0.0005110869476951104
            ],
            "neg_peak_relative_14": [
                0.0016765658026256416,
                0.00033531316052512835
            ],
            "neg_peak_relative_15": [
                0.0011641120916750266,
                0.00023282241833500535
            ],
            "neg_peak_relative_16": [
                0.0006636925795170573,
                0.00013273851590341146
            ],
            "neg_peak_relative_17": [
                0.00016611687634681045,
                3.322337526936209e-05
            ],
            "neg_peak_relative_18": [
                -1.4584981301126972e-05,
                2.9169962602253944e-06
            ],
            "neg_peak_relative_19": [
                -2.322822716931146e-05,
                4.645645433862292e-06
            ],
            "pos_peak_relative_0": [
                0.004227659027224459,
                0.0008455318054448918
            ],
            "pos_peak_relative_1": [
                0.006188715654610659,
                0.001237743130922132
            ],
            "pos_peak_relative_2": [
                0.009793461044244021,
                0.0019586922088488043
            ],
            "pos_peak_relative_3": [
                0.017507083652891768,
                0.0035014167305783537
            ],
            "pos_peak_relative_4": [
                0.038305817831381504,
                0.007661163566276301
            ],
            "pos_peak_relative_5": [
                0.12453723914106377,
                0.024907447828212755
            ],
            "pos_peak_relative_6": [
                1.0,
                0.2
            ],
            "pos_peak_relative_7": [
                0.39660999300428906,
                0.07932199860085781
            ],
            "pos_peak_relative_8": [
                0.6462080432715834,
                0.1292416086543167
            ],
            "pos_peak_relative_9": [
                0.21883876637889724,
                0.04376775327577945
            ],
            "pos_peak_relative_10": [
                0.09818234645325288,
                0.019636469290650577
            ],
            "pos_peak_relative_11": [
                0.04835847912421717,
                0.009671695824843434
            ],
            "pos_peak_relative_12": [
                0.02885476969837734,
                0.005770953939675468
            ],
            "pos_peak_relative_13": [
                0.019201486503482173,
                0.0038402973006964347
            ],
            "pos_peak_relative_14": [
                0.01379005418999765,
                0.0027580108379995304
            ],
            "pos_peak_relative_15": [
                0.01048642552434934,
                0.0020972851048698684
            ],
            "pos_peak_relative_16": [
                0.00833415671380882,
                0.001666831342761764
            ],
            "pos_peak_relative_17": [
                0.006874833428597562,
                0.0013749666857195125
            ],
            "pos_peak_relative_18": [
                0.005747362486319213,
                0.0011494724972638426
            ],
            "pos_peak_relative_19": [
                0.004793826350836182,
                0.0009587652701672366
            ],
            "neg_peak_diff_0": [
                -3.5e-05,
                7e-06
            ],
            "neg_peak_diff_1": [
                -4e-05,
                8.000000000000001e-06
            ],
            "neg_peak_diff_2": [
                -4e-05,
                8.000000000000001e-06
            ],
            "neg_peak_diff_3": [
                -4.5e-05,
                9e-06
            ],
            "neg_peak_diff_4": [
                -0.000435,
                8.7e-05
            ],
            "neg_peak_diff_5": [
                -0.00045,
                9e-05
            ],
            "neg_peak_diff_7": [
                0.000265,
                5.3e-05
            ],
            "neg_peak_diff_8": [
                0.001155,
                0.000231
            ],
            "neg_peak_diff_9": [
                0.001525,
                0.00030500000000000004
            ],
            "neg_peak_diff_10": [
                0.002105,
                0.00042100000000000004
            ],
            "neg_peak_diff_11": [
                0.003405,
                0.0006810000000000001
            ],
            "neg_peak_diff_12": [
                0.005405,
                0.0010810000000000001
            ],
            "neg_peak_diff_13": [
                0.006655,
                0.0013310000000000002
            ],
            "neg_peak_diff_14": [
                0.009935,
                0.001987
            ],
            "neg_peak_diff_15": [
                0.009935,
                0.001987
            ],
            "neg_peak_diff_16": [
                0.009935,
                0.001987
            ],
            "neg_peak_diff_17": [
                0.009935,
                0.001987
            ],
            "neg_peak_diff_18": [
                0.01,
                0.002
            ],
            "neg_peak_diff_19": [
                0.01,
                0.002
            ],
            "pos_peak_diff_0": [
                -5e-06,
                1.0000000000000002e-06
            ],
            "pos_peak_diff_1": [
                -5.5e-05,
                1.1000000000000001e-05
            ],
            "pos_peak_diff_2": [
                -0.000105,
                2.1000000000000002e-05
            ],
            "pos_peak_diff_3": [
                -0.000155,
                3.1e-05
            ],
            "pos_peak_diff_4": [
                -0.000255,
                5.1000000000000006e-05
            ],
            "pos_peak_diff_5": [
                -0.000105,
                2.1000000000000002e-05
            ],
            "pos_peak_diff_7": [
                -0.001525,
                0.00030500000000000004
            ],
            "pos_peak_diff_8": [
                -0.00144,
                0.000288
            ],
            "pos_peak_diff_9": [
                -0.0014,
                0.00028000000000000003
            ],
            "pos_peak_diff_10": [
                -0.001305,
                0.000261
            ],
            "pos_peak_diff_11": [
                -0.001205,
                0.000241
            ],
            "pos_peak_diff_12": [
                -0.001455,
                0.00029099999999999997
            ],
            "pos_peak_diff_13": [
                -0.001465,
                0.000293
            ],
            "pos_peak_diff_14": [
                -0.00147,
                0.000294
            ],
            "pos_peak_diff_15": [
                -0.00147,
                0.000294
            ],
            "pos_peak_diff_16": [
                -0.001475,
                0.000295
            ],
            "pos_peak_diff_17": [
                -0.001475,
                0.000295
            ],
            "pos_peak_diff_18": [
                -0.001475,
                0.000295
            ],
            "pos_peak_diff_19": [
                -0.00148,
                0.00029600000000000004
            ]
        }
    }
}