{
  "soma": {
    "IDrest_150": {
      "soma": {
        "mean_frequency": [
          9.733149484955499,
          0.48665747424777495
        ],
        "burst_number": [
          1.0,
          0.05
        ],
        "adaptation_index2": [
          0.10380093883600038,
          0.005190046941800019
        ],
        "ISI_CV": [
          0.4226200945879783,
          0.021131004729398915
        ],
        "ISI_log_slope": [
          0.8932905832949593,
          0.04466452916474797
        ],
        "inv_time_to_first_spike": [
          40.81632653048033,
          2.0408163265240167
        ],
        "inv_first_ISI": [
          81.30081300811159,
          4.06504065040558
        ],
        "inv_second_ISI": [
          63.69426751590908,
          3.184713375795454
        ],
        "inv_third_ISI": [
          28.81844380402803,
          1.4409221902014016
        ],
        "inv_fourth_ISI": [
          6.321112515801344,
          0.31605562579006724
        ],
        "inv_fifth_ISI": [
          6.548788474130799,
          0.32743942370653994
        ],
        "AP_amplitude": [
          67.34069656141033,
          3.3670348280705165
        ],
        "AHP_depth": [
          14.57418697784558,
          0.728709348892279
        ],
        "AHP_time_from_peak": [
          3.374999999999479,
          0.16874999999997398
        ]
      }
    },
    "IDrest_250": {
      "soma": {
        "mean_frequency": [
          15.08600888688617,
          0.7543004443443085
        ],
        "burst_number": [
          1.0,
          0.05
        ],
        "adaptation_index2": [
          0.05961506262686936,
          0.0029807531313434683
        ],
        "ISI_CV": [
          0.38521211803019983,
          0.019260605901509992
        ],
        "ISI_log_slope": [
          0.7547100930454225,
          0.03773550465227113
        ],
        "inv_time_to_first_spike": [
          104.72346460045182,
          5.236173230022591
        ],
        "inv_first_ISI": [
          137.21804511275076,
          6.860902255637538
        ],
        "inv_second_ISI": [
          115.07936507933891,
          5.753968253966946
        ],
        "inv_third_ISI": [
          94.14780763788525,
          4.707390381894263
        ],
        "inv_fourth_ISI": [
          41.63816689465537,
          2.0819083447327684
        ],
        "inv_fifth_ISI": [
          10.232351152978374,
          0.5116175576489187
        ],
        "AP_amplitude": [
          66.75279366232385,
          3.3376396831161927
        ],
        "AHP_depth": [
          14.948944880411318,
          0.747447244020566
        ],
        "AHP_time_from_peak": [
          3.4403947368414407,
          0.17201973684207206
        ]
      }
    },
    "IDrest_300": {
      "soma": {
        "mean_frequency": [
          16.22498647918074,
          0.811249323959037
        ],
        "burst_number": [
          1.0,
          0.05
        ],
        "adaptation_index2": [
          0.054030780117141415,
          0.002701539005857071
        ],
        "ISI_CV": [
          0.3751721849468517,
          0.018758609247342586
        ],
        "ISI_log_slope": [
          0.7325988904643752,
          0.036629944523218765
        ],
        "inv_time_to_first_spike": [
          129.87012986885878,
          6.49350649344294
        ],
        "inv_first_ISI": [
          149.25373134324965,
          7.462686567162483
        ],
        "inv_second_ISI": [
          128.20512820509904,
          6.410256410254952
        ],
        "inv_third_ISI": [
          106.38297872338006,
          5.319148936169004
        ],
        "inv_fourth_ISI": [
          54.94505494504245,
          2.747252747252123
        ],
        "inv_fifth_ISI": [
          11.641443538996189,
          0.5820721769498095
        ],
        "AP_amplitude": [
          66.74038850665762,
          3.3370194253328815
        ],
        "AHP_depth": [
          15.157650539040425,
          0.7578825269520213
        ],
        "AHP_time_from_peak": [
          3.499999999999242,
          0.1749999999999621
        ]
      }
    },
    "IV_-100": {
      "soma": {
        "Spikecount": [
          0.0,
          0.001
        ],
        "voltage_base": [
          -76.67433895964507,
          3.8337169479822535
        ],
        "voltage_deflection": [
          -11.956602180476168,
          0.5978301090238084
        ],
        "voltage_deflection_begin": [
          -11.98145586271562,
          0.599072793135781
        ],
        "steady_state_voltage_stimend": [
          -88.48142133417497,
          4.424071066708748
        ],
        "ohmic_input_resistance_vb_ssse": [
          34.72671286626441,
          1.7363356433132204
        ],
        "sag_amplitude": [
          3.449058260396413,
          0.17245291301982066
        ],
        "sag_ratio1": [
          0.22607672169069987,
          0.011303836084534995
        ],
        "sag_ratio2": [
          0.7739232783093001,
          0.03869616391546501
        ],
        "decay_time_constant_after_stim": [
          7.715481747681334,
          0.3857740873840667
        ]
      }
    },
    "IV_-20": {
      "soma": {
        "Spikecount": [
          0.0,
          0.001
        ],
        "voltage_base": [
          -76.67433895964507,
          3.8337169479822535
        ],
        "voltage_deflection": [
          -2.994357477983513,
          0.14971787389917565
        ],
        "voltage_deflection_begin": [
          -2.942434193884239,
          0.14712170969421196
        ],
        "steady_state_voltage_stimend": [
          -79.5188458891542,
          3.9759422944577105
        ],
        "ohmic_input_resistance_vb_ssse": [
          41.83098425748731,
          2.0915492128743653
        ],
        "sag_amplitude": [
          0.38403249620887436,
          0.01920162481044372
        ],
        "sag_ratio1": [
          0.11894929736639887,
          0.005947464868319943
        ],
        "sag_ratio2": [
          0.8810507026336012,
          0.04405253513168006
        ],
        "decay_time_constant_after_stim": [
          11.043965394109215,
          0.5521982697054607
        ]
      }
    },
    "APWaveform_260": {
      "soma": {
        "AP_amplitude": [
          73.94971875243397,
          3.6974859376216984
        ],
        "AP1_amp": [
          76.74047192701957,
          3.8370235963509787
        ],
        "AP2_amp": [
          75.41783505131133,
          3.7708917525655665
        ],
        "AP_duration_half_width": [
          0.5500000000001251,
          0.027500000000006256
        ],
        "AP_begin_width": [
          1.8500000000004206,
          0.09250000000002104
        ],
        "AP_begin_voltage": [
          -49.67838087805039,
          2.4839190439025196
        ],
        "AHP_depth": [
          14.062245894775014,
          0.7031122947387507
        ],
        "AHP_time_from_peak": [
          2.6750000000006082,
          0.13375000000003043
        ]
      }
    }
  },
  "extra": {
    "IDrest_150": {
      "soma": {
        "mean_frequency": [
          9.733149484955499,
          0.48665747424777495
        ],
        "burst_number": [
          1.0,
          0.05
        ],
        "adaptation_index2": [
          0.10380093883600038,
          0.005190046941800019
        ],
        "ISI_CV": [
          0.4226200945879783,
          0.021131004729398915
        ],
        "ISI_log_slope": [
          0.8932905832949593,
          0.04466452916474797
        ],
        "inv_time_to_first_spike": [
          40.81632653048033,
          2.0408163265240167
        ],
        "inv_first_ISI": [
          81.30081300811159,
          4.06504065040558
        ],
        "inv_second_ISI": [
          63.69426751590908,
          3.184713375795454
        ],
        "inv_third_ISI": [
          28.81844380402803,
          1.4409221902014016
        ],
        "inv_fourth_ISI": [
          6.321112515801344,
          0.31605562579006724
        ],
        "inv_fifth_ISI": [
          6.548788474130799,
          0.32743942370653994
        ],
        "AP_amplitude": [
          67.34069656141033,
          3.3670348280705165
        ],
        "AHP_depth": [
          14.57418697784558,
          0.728709348892279
        ],
        "AHP_time_from_peak": [
          3.374999999999479,
          0.16874999999997398
        ]
      }
    },
    "IDrest_250": {
      "soma": {
        "mean_frequency": [
          15.08600888688617,
          0.7543004443443085
        ],
        "burst_number": [
          1.0,
          0.05
        ],
        "adaptation_index2": [
          0.05961506262686936,
          0.0029807531313434683
        ],
        "ISI_CV": [
          0.38521211803019983,
          0.019260605901509992
        ],
        "ISI_log_slope": [
          0.7547100930454225,
          0.03773550465227113
        ],
        "inv_time_to_first_spike": [
          104.72346460045182,
          5.236173230022591
        ],
        "inv_first_ISI": [
          137.21804511275076,
          6.860902255637538
        ],
        "inv_second_ISI": [
          115.07936507933891,
          5.753968253966946
        ],
        "inv_third_ISI": [
          94.14780763788525,
          4.707390381894263
        ],
        "inv_fourth_ISI": [
          41.63816689465537,
          2.0819083447327684
        ],
        "inv_fifth_ISI": [
          10.232351152978374,
          0.5116175576489187
        ],
        "AP_amplitude": [
          66.75279366232385,
          3.3376396831161927
        ],
        "AHP_depth": [
          14.948944880411318,
          0.747447244020566
        ],
        "AHP_time_from_peak": [
          3.4403947368414407,
          0.17201973684207206
        ]
      }
    },
    "IDrest_300": {
      "soma": {
        "mean_frequency": [
          16.22498647918074,
          0.811249323959037
        ],
        "burst_number": [
          1.0,
          0.05
        ],
        "adaptation_index2": [
          0.054030780117141415,
          0.002701539005857071
        ],
        "ISI_CV": [
          0.3751721849468517,
          0.018758609247342586
        ],
        "ISI_log_slope": [
          0.7325988904643752,
          0.036629944523218765
        ],
        "inv_time_to_first_spike": [
          129.87012986885878,
          6.49350649344294
        ],
        "inv_first_ISI": [
          149.25373134324965,
          7.462686567162483
        ],
        "inv_second_ISI": [
          128.20512820509904,
          6.410256410254952
        ],
        "inv_third_ISI": [
          106.38297872338006,
          5.319148936169004
        ],
        "inv_fourth_ISI": [
          54.94505494504245,
          2.747252747252123
        ],
        "inv_fifth_ISI": [
          11.641443538996189,
          0.5820721769498095
        ],
        "AP_amplitude": [
          66.74038850665762,
          3.3370194253328815
        ],
        "AHP_depth": [
          15.157650539040425,
          0.7578825269520213
        ],
        "AHP_time_from_peak": [
          3.499999999999242,
          0.1749999999999621
        ]
      },
      "MEA": {
        "peak_to_valley_36": [
          0.00063,
          3.15e-05
        ],
        "peak_to_valley_29": [
          0.000995,
          4.975e-05
        ],
        "peak_to_valley_24": [
          -0.0009400000000000001,
          4.7000000000000004e-05
        ],
        "peak_to_valley_64": [
          -0.0009100000000000001,
          4.550000000000001e-05
        ],
        "peak_to_valley_43": [
          -0.000885,
          4.4250000000000005e-05
        ],
        "peak_to_valley_44": [
          -0.0009350000000000001,
          4.6750000000000005e-05
        ],
        "peak_to_valley_2": [
          -0.00102,
          5.1000000000000006e-05
        ],
        "peak_trough_ratio_36": [
          1.7532247413016995,
          0.08766123706508498
        ],
        "peak_trough_ratio_29": [
          2.6966981400836194,
          0.13483490700418096
        ],
        "peak_trough_ratio_24": [
          0.21862189437682852,
          0.010931094718841426
        ],
        "peak_trough_ratio_64": [
          0.3448137208567769,
          0.017240686042838845
        ],
        "peak_trough_ratio_43": [
          0.2891008983913643,
          0.014455044919568217
        ],
        "peak_trough_ratio_44": [
          0.2055720360532723,
          0.010278601802663614
        ],
        "peak_trough_ratio_2": [
          0.127032591821346,
          0.0063516295910673
        ],
        "halfwidth_36": [
          0.001265,
          6.325e-05
        ],
        "halfwidth_29": [
          0.00529,
          0.00026450000000000003
        ],
        "halfwidth_24": [
          -0.006175000000000001,
          0.00030875000000000005
        ],
        "halfwidth_64": [
          -0.006065,
          0.00030325
        ],
        "halfwidth_43": [
          -0.006220000000000001,
          0.0003110000000000001
        ],
        "halfwidth_44": [
          -0.006175000000000001,
          0.00030875000000000005
        ],
        "halfwidth_2": [
          -0.005655,
          0.00028275
        ],
        "repolarization_slope_36": [
          0.2542561362005838,
          0.01271280681002919
        ],
        "repolarization_slope_29": [
          1.7542950109387088,
          0.08771475054693545
        ],
        "repolarization_slope_24": [
          32.071567730540686,
          1.6035783865270343
        ],
        "repolarization_slope_64": [
          2.8195393703862135,
          0.14097696851931069
        ],
        "repolarization_slope_43": [
          14.184139401244485,
          0.7092069700622243
        ],
        "repolarization_slope_44": [
          36.39803955748442,
          1.819901977874221
        ],
        "repolarization_slope_2": [
          9.460168286529168,
          0.4730084143264584
        ],
        "recovery_slope_36": [
          -0.28013399770699526,
          0.014006699885349763
        ],
        "recovery_slope_29": [
          -3.0052758979379197,
          0.150263794896896
        ],
        "recovery_slope_24": [
          -15.842270461340615,
          0.7921135230670308
        ],
        "recovery_slope_64": [
          -4.276846901923488,
          0.2138423450961744
        ],
        "recovery_slope_43": [
          -14.650770691222242,
          0.7325385345611122
        ],
        "recovery_slope_44": [
          -18.958630497522204,
          0.9479315248761102
        ],
        "recovery_slope_2": [
          -0.6472135870043298,
          0.03236067935021649
        ],
        "neg_peak_diff_36": [
          -0.00066,
          3.3e-05
        ],
        "neg_peak_diff_29": [
          -0.000785,
          3.9250000000000005e-05
        ],
        "neg_peak_diff_24": [
          5.5e-05,
          2.7500000000000004e-06
        ],
        "neg_peak_diff_64": [
          0.000115,
          5.750000000000001e-06
        ],
        "neg_peak_diff_43": [
          -5e-05,
          2.5e-06
        ],
        "neg_peak_diff_44": [
          0.0,
          0.0
        ],
        "neg_peak_diff_2": [
          -0.000115,
          5.750000000000001e-06
        ],
        "pos_peak_diff_36": [
          0.000105,
          5.2500000000000006e-06
        ],
        "pos_peak_diff_29": [
          0.000345,
          1.725e-05
        ],
        "pos_peak_diff_24": [
          -0.00075,
          3.7500000000000003e-05
        ],
        "pos_peak_diff_64": [
          -0.00066,
          3.3e-05
        ],
        "pos_peak_diff_43": [
          -0.0008,
          4e-05
        ],
        "pos_peak_diff_44": [
          -0.0008,
          4e-05
        ],
        "pos_peak_diff_2": [
          -0.001,
          5e-05
        ],
        "neg_peak_relative_36": [
          0.0035222009217261573,
          0.00017611004608630789
        ],
        "neg_peak_relative_29": [
          0.03492477121866135,
          0.0017462385609330678
        ],
        "neg_peak_relative_24": [
          0.9503322319269359,
          0.0475166115963468
        ],
        "neg_peak_relative_64": [
          0.09886508895623658,
          0.0049432544478118295
        ],
        "neg_peak_relative_43": [
          0.4863890752566006,
          0.02431945376283003
        ],
        "neg_peak_relative_44": [
          1.0,
          0.05
        ],
        "neg_peak_relative_2": [
          0.09798462723847128,
          0.0048992313619235645
        ],
        "pos_peak_relative_36": [
          0.008771561726472936,
          0.0004385780863236468
        ],
        "pos_peak_relative_29": [
          0.1337799755530255,
          0.006688998777651276
        ],
        "pos_peak_relative_24": [
          0.29511706236123075,
          0.014755853118061539
        ],
        "pos_peak_relative_64": [
          0.048423113168695874,
          0.002421155658434794
        ],
        "pos_peak_relative_43": [
          0.19973697109901198,
          0.009986848554950599
        ],
        "pos_peak_relative_44": [
          0.29200429814298157,
          0.014600214907149078
        ],
        "pos_peak_relative_2": [
          0.01768065339807091,
          0.0008840326699035456
        ],
        "neg_image_36": [
          -0.0060757104854638495,
          0.0003037855242731925
        ],
        "neg_image_29": [
          -0.07831360771308553,
          0.003915680385654276
        ],
        "neg_image_24": [
          0.9111133156386545,
          0.04555566578193273
        ],
        "neg_image_64": [
          0.09111374680854567,
          0.004555687340427284
        ],
        "neg_image_43": [
          0.47763248317442736,
          0.02388162415872137
        ],
        "neg_image_44": [
          1.0,
          0.05
        ],
        "neg_image_2": [
          0.07368388201586544,
          0.003684194100793272
        ],
        "pos_image_36": [
          0.00702658779635822,
          0.000351329389817911
        ],
        "pos_image_29": [
          0.0636111648819087,
          0.003180558244095435
        ],
        "pos_image_24": [
          -0.7177428630341496,
          0.03588714315170748
        ],
        "pos_image_64": [
          -0.07988029921963553,
          0.0039940149609817765
        ],
        "pos_image_43": [
          -0.6303385396820814,
          0.03151692698410407
        ],
        "pos_image_44": [
          -1.074598430074093,
          0.05372992150370465
        ],
        "pos_image_2": [
          -0.13780759377913487,
          0.006890379688956744
        ]
      }
    },
    "IV_-100": {
      "soma": {
        "Spikecount": [
          0.0,
          0.001
        ],
        "voltage_base": [
          -76.67433895964507,
          3.8337169479822535
        ],
        "voltage_deflection": [
          -11.956602180476168,
          0.5978301090238084
        ],
        "voltage_deflection_begin": [
          -11.98145586271562,
          0.599072793135781
        ],
        "steady_state_voltage_stimend": [
          -88.48142133417497,
          4.424071066708748
        ],
        "ohmic_input_resistance_vb_ssse": [
          34.72671286626441,
          1.7363356433132204
        ],
        "sag_amplitude": [
          3.449058260396413,
          0.17245291301982066
        ],
        "sag_ratio1": [
          0.22607672169069987,
          0.011303836084534995
        ],
        "sag_ratio2": [
          0.7739232783093001,
          0.03869616391546501
        ],
        "decay_time_constant_after_stim": [
          7.715481747681334,
          0.3857740873840667
        ]
      }
    },
    "IV_-20": {
      "soma": {
        "Spikecount": [
          0.0,
          0.001
        ],
        "voltage_base": [
          -76.67433895964507,
          3.8337169479822535
        ],
        "voltage_deflection": [
          -2.994357477983513,
          0.14971787389917565
        ],
        "voltage_deflection_begin": [
          -2.942434193884239,
          0.14712170969421196
        ],
        "steady_state_voltage_stimend": [
          -79.5188458891542,
          3.9759422944577105
        ],
        "ohmic_input_resistance_vb_ssse": [
          41.83098425748731,
          2.0915492128743653
        ],
        "sag_amplitude": [
          0.38403249620887436,
          0.01920162481044372
        ],
        "sag_ratio1": [
          0.11894929736639887,
          0.005947464868319943
        ],
        "sag_ratio2": [
          0.8810507026336012,
          0.04405253513168006
        ],
        "decay_time_constant_after_stim": [
          11.043965394109215,
          0.5521982697054607
        ]
      }
    },
    "APWaveform_260": {
      "soma": {
        "AP_amplitude": [
          73.94971875243397,
          3.6974859376216984
        ],
        "AP1_amp": [
          76.74047192701957,
          3.8370235963509787
        ],
        "AP2_amp": [
          75.41783505131133,
          3.7708917525655665
        ],
        "AP_duration_half_width": [
          0.5500000000001251,
          0.027500000000006256
        ],
        "AP_begin_width": [
          1.8500000000004206,
          0.09250000000002104
        ],
        "AP_begin_voltage": [
          -49.67838087805039,
          2.4839190439025196
        ],
        "AHP_depth": [
          14.062245894775014,
          0.7031122947387507
        ],
        "AHP_time_from_peak": [
          2.6750000000006082,
          0.13375000000003043
        ]
      }
    }
  }
}